vendy_cli/__init__.py
vendy_cli/cmd.py
vendy_cli-0.2.4.dist-info/LICENSE
vendy_cli-0.2.4.dist-info/METADATA
vendy_cli-0.2.4.dist-info/WHEEL
vendy_cli-0.2.4.dist-info/entry_points.txt
vendy_cli-0.2.4.dist-info/RECORD
