Metadata-Version: 2.3
Name: vendy-cli
Version: 0.2.4
Summary: Code Framework Vending machine
Author: Russell Whelan
Author-email: russell.whelan@gmail.com
Requires-Python: >=3.12,<4.0
Classifier: Programming Language :: Python :: 3
Classifier: Programming Language :: Python :: 3.12
Classifier: Programming Language :: Python :: 3.13
Requires-Dist: cookiecutter (>=2.6.0,<3.0.0)
Requires-Dist: gitpython (>=3.1.44,<4.0.0)
Requires-Dist: pathlib (>=1.0.1,<2.0.0)
Requires-Dist: pyyaml (>=6.0.2,<7.0.0)
Requires-Dist: rich (>=13.9.4,<14.0.0)
Requires-Dist: setuptools (>=76.0.0,<77.0.0)
Requires-Dist: tabulate (>=0.9.0,<0.10.0)
Requires-Dist: typer (>=0.15.2,<0.16.0)
